pyfind/__init__.py
pyfind/_find.py
pyfind/_findsub.py
pyfind/_retrieve.py
pyfind-0.3.22.dist-info/LICENSE
pyfind-0.3.22.dist-info/METADATA
pyfind-0.3.22.dist-info/WHEEL
pyfind-0.3.22.dist-info/top_level.txt
pyfind-0.3.22.dist-info/RECORD
