Metadata-Version: 2.1
Name: pyfind
Version: 0.3.22
Summary: A python import util for traversing directories
Home-page: UNKNOWN
Author: Alexander Angelidis
Author-email: alex.m.angelidis@gmail.com
License: UNKNOWN
Platform: UNKNOWN
Classifier: Programming Language :: Python :: 3
Classifier: License :: OSI Approved :: GNU Affero General Public License v3
Classifier: Operating System :: Microsoft :: Windows
